entrypoint
pywss
