Metadata-Version: 2.1
Name: pywss
Version: 0.2.3
Summary: This Is A Web/WebSocket Server By Python
Home-page: https://github.com/czasg/pywss
Author: czasg
Author-email: 972542644@qq.com
License: MIT
Classifier: Programming Language :: Python :: 3.8
License-File: LICENSE
Requires-Dist: loggus>=0.1.1
Requires-Dist: pydantic
